{
  "id": "1236050016221663232",
  "name": "DSP Report",
  "pid": "0",
  "orgId": "1",
  "level": null,
  "nodeType": "leaf",
  "type": "dashboard",
  "canvasStyleData": "{\"width\": 1920, \"height\": 1080, \"selfAdaption\": true, \"auxiliaryMatrix\": true, \"openCommonStyle\": true, \"panel\": {\"themeColor\": \"light\", \"color\": \"#ffffff\", \"imageUrl\": \"\", \"borderRadius\": 0}, \"dashboard\": {}}",
  "componentData": "[]",
  "mobileLayout": false,
  "extFlag": 0,
  "status": 0,
  "selfWatermarkStatus": false,
  "sort": 0,
  "createTime": 1774863754197,
  "createBy": "1",
  "creatorName": "管理员",
  "updateTime": 1774863754197,
  "updateBy": "1",
  "updateName": null,
  "remark": null,
  "source": null,
  "deleteFlag": false,
  "deleteTime": null,
  "deleteBy": null,
  "version": 3,
  "contentId": "0",
  "checkVersion": "1",
  "canvasViewInfo": {},
  "extendDataInfo": {},
  "reportFilterInfo": {},
  "watermarkInfo": {
    "id": "system_default",
    "version": "1.0",
    "settingContent": "{\"enable\":false,\"enablePanelCustom\":true,\"type\":\"custom\",\"content\":\"水印\",\"watermark_color\":\"#DD1010\",\"watermark_x_space\":12,\"watermark_y_space\":36,\"watermark_fontsize\":15}",
    "createBy": "admin",
    "createTime": null
  },
  "weight": 9,
  "ext": 0,
  "appData": null
}